visu3d/__init__.py
visu3d/array_dataclass.py
visu3d/dc_arrays/camera.py
visu3d/dc_arrays/camera_spec.py
visu3d/dc_arrays/point.py
visu3d/dc_arrays/ray.py
visu3d/dc_arrays/transformation.py
visu3d/math/__init__.py
visu3d/math/coord_utils.py
visu3d/math/interp_utils.py
visu3d/math/math_utils.py
visu3d/math/rotation_utils.py
visu3d/plotly/__init__.py
visu3d/plotly/auto_plot.py
visu3d/plotly/fig_config_utils.py
visu3d/plotly/fig_utils.py
visu3d/plotly/traces_builder.py
visu3d/utils/__init__.py
visu3d/utils/file_utils.py
visu3d/utils/lazy_imports.py
visu3d/utils/np_utils.py
visu3d/utils/py_utils.py
visu3d-1.5.3.dist-info/LICENSE
visu3d-1.5.3.dist-info/WHEEL
visu3d-1.5.3.dist-info/METADATA
visu3d-1.5.3.dist-info/RECORD
