Metadata-Version: 2.1
Name: visu3d
Version: 1.5.3
Summary: 3d geometry made easy.
Keywords: 3d,visu3d,visualization,neural rendering,nerf
Author-email: Visu3d team <visu3d@google.com>
Requires-Python: >=3.9
Classifier: Programming Language :: Python :: 3
Classifier: Programming Language :: Python :: 3 :: Only
Classifier: License :: OSI Approved :: Apache Software License
Classifier: Intended Audience :: Developers
Classifier: Intended Audience :: Science/Research
Classifier: Topic :: Scientific/Engineering :: Visualization
Classifier: Topic :: Software Development :: Libraries :: Python Modules
Requires-Dist: dataclass_array
Requires-Dist: einops
Requires-Dist: etils[edc,enp,epath,epy,etree]
Requires-Dist: numpy
Requires-Dist: typing_extensions
Requires-Dist: pytest>=3.4 ; extra == "dev"
Requires-Dist: pytest-xdist ; extra == "dev"
Requires-Dist: pylint>=2.6.0 ; extra == "dev"
Requires-Dist: pyink ; extra == "dev"
Requires-Dist: chex ; extra == "dev"
Requires-Dist: jax[cpu] ; extra == "dev"
Requires-Dist: jupyter ; extra == "dev"
Requires-Dist: tf-nightly ; extra == "dev"
Requires-Dist: tensorflow_datasets ; extra == "dev"
Requires-Dist: torch ; extra == "dev"
Requires-Dist: plotly ; extra == "dev"
Requires-Dist: scipy ; extra == "dev"
Requires-Dist: sphinx-apitree[ext] ; extra == "docs"
Requires-Dist: visu3d[dev] ; extra == "docs"
Requires-Dist: scipy>=1.10 ; extra == "docs"
Project-URL: changelog, https://github.com/google-research/visu3d/blob/main/CHANGELOG.md
Project-URL: documentation, https://visu3d.readthedocs.io
Project-URL: homepage, https://github.com/google-research/visu3d
Project-URL: repository, https://github.com/google-research/visu3d
Provides-Extra: dev
Provides-Extra: docs
